HelmFromComposer/HelmFromComposer.py
HelmFromComposer/__init__.py
HelmFromComposer/yaml_templates.py
pyhelmgen-1.4.dist-info/LICENSE
pyhelmgen-1.4.dist-info/METADATA
pyhelmgen-1.4.dist-info/WHEEL
pyhelmgen-1.4.dist-info/top_level.txt
pyhelmgen-1.4.dist-info/RECORD
